Workbook

Sheet Read Me
B2: The PR Hub — Build-Out Financial Model
B3: Companion to the Build-Out Blueprint. Move the levers, watch the firm build itself out of its own cash flow.
B5: HOW TO USE THIS MODEL
B6: 1. Go to the 'Assumptions' tab. Every cell shaded yellow is yours to edit — pricing, salaries, overheads.
B7: 2. 'Unit Economics' shows what a single senior account lead earns the firm at capacity. This is why each hire pays for itself.
B8: 3. 'Stage Plan' is the phased build-out — Stage 0 (you, now) through Stage 4 (built to sell). Edit the blue driver cells to model your own path.
B9: 4. After editing, everything recalculates automatically. No formula should ever be overwritten.
B11: THE COLOUR CODE
B12: Blue text = an input / lever you can change.
B13: Yellow fill = a key assumption — the numbers that most move the outcome. Start here.
B14: Black text = a formula. Leave it alone; it does the work.
B15: Green text = a value pulled from another tab.
... B21: Prepared as strategic counsel for the Founder & CEO. v1.

Sheet Assumptions
A1: ASSUMPTIONS — edit the yellow cells
B3: REVENUE LEVERS
B4: Average monthly retainer (A$/mo) | C4: 11000 | D4: Your target: A$10–12k
B5: Retainers per lead at capacity | C5: 5 | D5: Elite senior-led norm is 4–5
B6: Workshop / speaking fee (A$ each) | C6: 8000 | D6: EO / YPO paid sessions
B7: Earned-media project — avg (A$ each) | C7: 15000 | D7: Tiered publication packages
B9: PEOPLE COSTS (fully loaded, A$/yr)
B10: Senior account lead | C10: 190000 | D10: 12+ yrs; incl. on-costs & bonus
B11: Strategy Associate / AI Producer | C11: 85000 | D11: AI-native; runs the bench
B12: Administrative assistant | C12: 70000
B13: Integrator (COO/GM) — full-time | C13: 220000 | D13: Fractional = a fraction of this
B14: Founder package / draw | C14: 200000 | D14: Market pay so EBITDA is honest
B16: OTHER COSTS
B17: AI bench & tools per client (A$/yr) | C17: 3000 | D17: Scales with client count
B18: Fixed overheads (A$/yr) | C18: 60000 | D18: Software, insurance, brand, travel
B19: Leads per Strategy Associate | C19: 3 | D19: 1 associate supports ~3 leads

Sheet Unit Economics
A1: UNIT ECONOMICS — one senior lead at capacity
B2: Why every hire pays for itself. All figures pull from Assumptions.
B3: Retainers carried per lead | C3: =Assumptions!C5
B4: Annual revenue per lead | C4: =C3*Assumptions!C4*12 | D4: retainers × price × 12 months
B6: Less: senior lead salary | C6: =-Assumptions!C10
B7: Less: Strategy Associate (shared) | C7: =-Assumptions!C11/Assumptions!C19 | D7: one associate supports ~3 leads
B8: Less: AI bench & tools | C8: =-C3*Assumptions!C17 | D8: per client served
B9: Contribution margin per lead | C9: =C4+C6+C7+C8
B10: Contribution margin % | C10: =C9/C4
B12: Read: each senior lead throws off roughly this much before firm overhead.
B13: That surplus is what funds the Integrator, the admin team, and your own package.

Sheet Stage Plan
A1: STAGE PLAN — the phased build-out (annualised run-rate per stage)
C3: Stage 0 | D3: Stage 1 | E3: Stage 2 | F3: Stage 3 | G3: Stage 4
B4: DRIVERS (edit the blue cells) | C4: Prove funnel | D4: Buy back time | E4: First lead | F4: The engine | G4: Built to sell
B5: Retainer clients (end of stage) | C5: 3 | D5: 5 | E5: 9 | F5: 18 | G5: 30
B6: Senior account leads | C6: 0 | D6: 0 | E6: 1 | F6: 3 | G6: 6
B7: Strategy Associates | C7: 0 | D7: 0 | E7: 1 | F7: 1 | G7: 2
B8: Accounts founder still delivers | C8: 3 | D8: 5 | E8: 4 | F8: 3 | G8: 0
B9: Integrator (FTE: 0 / 0.4 / 1) | C9: 0 | D9: 0.4 | E9: 0.4 | F9: 1 | G9: 1
B10: Admin (FTE) | C10: 0.5 | D10: 1 | E10: 1 | F10: 1 | G10: 1.5
B11: Workshops / speaking per year | C11: 10 | D11: 16 | E11: 18 | F11: 16 | G11: 12
B12: Earned-media projects per year | C12: 4 | D12: 6 | E12: 8 | F12: 10 | G12: 12
B13: Delivery capacity check (leads×cap + founder) | C13: =C6*Assumptions!$C$5+C8 | D13: =D6*Assumptions!$C$5+D8 | E13: =E6*Assumptions!$C$5+E8 | F13: =F6*Assumptions!$C$5+F8 | G13: =G6*Assumptions!$C$5+G8
B15: REVENUE (A$/yr)
B16: Recurring — retainers | C16: =C5*Assumptions!$C$4*12 | D16: =D5*Assumptions!$C$4*12 | E16: =E5*Assumptions!$C$4*12 | F16: =F5*Assumptions!$C$4*12 | G16: =G5*Assumptions!$C$4*12
B17: Workshops & speaking | C17: =C11*Assumptions!$C$6 | D17: =D11*Assumptions!$C$6 | E17: =E11*Assumptions!$C$6 | F17: =F11*Assumptions!$C$6 | G17: =G11*Assumptions!$C$6
B18: Earned-media projects | C18: =C12*Assumptions!$C$7 | D18: =D12*Assumptions!$C$7 | E18: =E12*Assumptions!$C$7 | F18: =F12*Assumptions!$C$7 | G18: =G12*Assumptions!$C$7
B19: Total revenue | C19: =SUM(C16:C18) | D19: =SUM(D16:D18) | E19: =SUM(E16:E18) | F19: =SUM(F16:F18) | G19: =SUM(G16:G18)
B21: COSTS (A$/yr)
B22: Founder package | C22: =Assumptions!$C$14 | D22: =Assumptions!$C$14 | E22: =Assumptions!$C$14 | F22: =Assumptions!$C$14 | G22: =Assumptions!$C$14
B23: Senior account leads | C23: =C6*Assumptions!$C$10 | D23: =D6*Assumptions!$C$10 | E23: =E6*Assumptions!$C$10 | F23: =F6*Assumptions!$C$10 | G23: =G6*Assumptions!$C$10
B24: Strategy Associates | C24: =C7*Assumptions!$C$11 | D24: =D7*Assumptions!$C$11 | E24: =E7*Assumptions!$C$11 | F24: =F7*Assumptions!$C$11 | G24: =G7*Assumptions!$C$11
B25: Integrator | C25: =C9*Assumptions!$C$13 | D25: =D9*Assumptions!$C$13 | E25: =E9*Assumptions!$C$13 | F25: =F9*Assumptions!$C$13 | G25: =G9*Assumptions!$C$13
B26: Admin | C26: =C10*Assumptions!$C$12 | D26: =D10*Assumptions!$C$12 | E26: =E10*Assumptions!$C$12 | F26: =F10*Assumptions!$C$12 | G26: =G10*Assumptions!$C$12
B27: AI bench & tools | C27: =C5*Assumptions!$C$17 | D27: =D5*Assumptions!$C$17 | E27: =E5*Assumptions!$C$17 | F27: =F5*Assumptions!$C$17 | G27: =G5*Assumptions!$C$17
B28: Fixed overheads | C28: =Assumptions!$C$18 | D28: =Assumptions!$C$18 | E28: =Assumptions!$C$18 | F28: =Assumptions!$C$18 | G28: =Assumptions!$C$18
B29: Total costs | C29: =SUM(C22:C28) | D29: =SUM(D22:D28) | E29: =SUM(E22:E28) | F29: =SUM(F22:F28) | G29: =SUM(G22:G28)
B31: EBITDA (after founder pay) | C31: =C19-C29 | D31: =D19-D29 | E31: =E19-E29 | F31: =F19-F29 | G31: =G19-G29
B32: EBITDA margin % | C32: =IF(C19=0,0,C31/C19) | D32: =IF(D19=0,0,D31/D19) | E32: =IF(E19=0,0,E31/E19) | F32: =IF(F19=0,0,F31/F19) | G32: =IF(G19=0,0,G31/G19)
B33: Recurring revenue / month (MRR) | C33: =C16/12 | D33: =D16/12 | E33: =E16/12 | F33: =F16/12 | G33: =G16/12
B35: Advance-stage trigger | C35: A$25–40k/mo recurring | D35: 3–4 retainers signed | E35: Can't service next client | F35: Lead #1 at 4–5 load pts | G35: Built to sell
